<SOAP-ENV:Envelope xmlns:SOAP-ENV="http://schemas.xmlsoap.org/soap/envelope/">
    <SOAP-ENV:Header/>
    <SOAP-ENV:Body>
        <ns2:getExchangeRateResponse xmlns:ns2="http://spring.io/guides/gs-producing-web-service">
            <ns2:ExchangeRate>
                <ns2:name>USDtoEUR</ns2:name>
                <ns2:ExchangeRate>0.91</ns2:ExchangeRate>
                <ns2:fromCCY>USD</ns2:fromCCY>
                <ns2:toCCY>EUR</ns2:toCCY>
            </ns2:ExchangeRate>
        </ns2:getExchangeRateResponse>
    </SOAP-ENV:Body>
</SOAP-ENV:Envelope>